senren/cli/batch_job_cli.py
senren/cli/load_modules.py
senren/cli/python_env_cli.py
senren/cli/senren_cli.py
senren/cli/state_cli.py
senren/config.py
senren/custom_exceptions.py
senren/data_source.py
senren/entity.py
senren/feature.py
senren/feature_reference.py
senren/feature_service.py
senren/feature_store/v1/registry_pb2.py
senren/feature_store/v1/registry_pb2.pyi
senren/feature_store/v1/registry_pb2_grpc.py
senren/feature_store/v1/registry_pb2_grpc.pyi
senren/feature_store/v1/service_pb2.py
senren/feature_store/v1/service_pb2.pyi
senren/feature_store/v1/service_pb2_grpc.py
senren/feature_store/v1/service_pb2_grpc.pyi
senren/feature_store/v1/specs/alerts_pb2.py
senren/feature_store/v1/specs/alerts_pb2.pyi
senren/feature_store/v1/specs/alerts_pb2_grpc.py
senren/feature_store/v1/specs/alerts_pb2_grpc.pyi
senren/feature_store/v1/specs/data_source_pb2.py
senren/feature_store/v1/specs/data_source_pb2.pyi
senren/feature_store/v1/specs/data_source_pb2_grpc.py
senren/feature_store/v1/specs/data_source_pb2_grpc.pyi
senren/feature_store/v1/specs/entity_pb2.py
senren/feature_store/v1/specs/entity_pb2.pyi
senren/feature_store/v1/specs/entity_pb2_grpc.py
senren/feature_store/v1/specs/entity_pb2_grpc.pyi
senren/feature_store/v1/specs/feature_pb2.py
senren/feature_store/v1/specs/feature_pb2.pyi
senren/feature_store/v1/specs/feature_pb2_grpc.py
senren/feature_store/v1/specs/feature_pb2_grpc.pyi
senren/feature_store/v1/specs/feature_service_pb2.py
senren/feature_store/v1/specs/feature_service_pb2.pyi
senren/feature_store/v1/specs/feature_service_pb2_grpc.py
senren/feature_store/v1/specs/feature_service_pb2_grpc.pyi
senren/feature_store/v1/specs/feature_view_pb2.py
senren/feature_store/v1/specs/feature_view_pb2.pyi
senren/feature_store/v1/specs/feature_view_pb2_grpc.py
senren/feature_store/v1/specs/feature_view_pb2_grpc.pyi
senren/feature_store/v1/specs/metadata_pb2.py
senren/feature_store/v1/specs/metadata_pb2.pyi
senren/feature_store/v1/specs/metadata_pb2_grpc.py
senren-0.1.1.dist-info/METADATA
senren-0.1.1.dist-info/WHEEL
senren-0.1.1.dist-info/entry_points.txt
senren-0.1.1.dist-info/RECORD
